vinnie/__init__.py
vinnie/base.py
vinnie/cli.py
vinnie/config.py
vinnie/exceptions.py
vinnie/backends/__init__.py
vinnie/backends/base.py
vinnie/backends/git.py
vinnie/backends/github.py
vinnie/backends/gitlab.py
vinnie-0.9.0.dist-info/METADATA
vinnie-0.9.0.dist-info/WHEEL
vinnie-0.9.0.dist-info/entry_points.txt
vinnie-0.9.0.dist-info/licenses/AUTHORS.txt
vinnie-0.9.0.dist-info/licenses/LICENSE
vinnie-0.9.0.dist-info/RECORD
