Metadata-Version: 2.4
Name: vinnie
Version: 0.9.0
Summary: A small utility to handle semantic versioning using only git tags
Project-URL: Homepage, https://github.com/revsys/vinnie/
Project-URL: Issues, https://github.com/revsys/vinine/issues
Author-email: Frank Wiles <frank@revsys.com>
License: BSD License
License-File: AUTHORS.txt
License-File: LICENSE
Classifier: Development Status :: 5 - Production/Stable
Classifier: Environment :: Console
Classifier: License :: OSI Approved :: BSD License
Classifier: Programming Language :: Python :: 3
Classifier: Topic :: Software Development
Classifier: Topic :: System :: Systems Administration
Requires-Python: >=3.9
Requires-Dist: click<9.0,>=7.1
Requires-Dist: gitpython>=3.1.37
Requires-Dist: semver>=2.13.0
Provides-Extra: test
Requires-Dist: pytest-cov==3.0.0; extra == 'test'
Requires-Dist: pytest-sugar==0.9.5; extra == 'test'
Requires-Dist: pytest==7.1.3; extra == 'test'
